track/__init__.py
track/__main__.py
track/app_constants.py
track/app_functions.py
track/cli.py
track/database.py
track/db_handler.py
track/job_application.py
track/job_tracker.py
track/logger.py
track/report_cli.py
track/reporter.py
track/update_cli.py
track_job_applications-1.0.0.dist-info/entry_points.txt
track_job_applications-1.0.0.dist-info/LICENSE.md
track_job_applications-1.0.0.dist-info/WHEEL
track_job_applications-1.0.0.dist-info/METADATA
track_job_applications-1.0.0.dist-info/RECORD
