Metadata-Version: 2.1
Name: track-job-applications
Version: 1.0.0
Summary: A CLI application to help you track job applications and provide metrics on them.
Home-page: https://github.com/Aditya-Gupta1/track-job-applications
License: MIT
Keywords: python,typer,cli,job tracker
Author: Aditya Gupta
Author-email: guptaaditya008@gmail.com
Maintainer: Aditya Gupta
Maintainer-email: guptaaditya008@gmail.com
Requires-Python: >=3.8,<4.0
Classifier: License :: OSI Approved :: MIT License
Classifier: Programming Language :: Python :: 3
Classifier: Programming Language :: Python :: 3.8
Classifier: Programming Language :: Python :: 3.9
Classifier: Programming Language :: Python :: 3.10
Classifier: Programming Language :: Python :: 3.11
Requires-Dist: SQLAlchemy (>=1.4.41,<2.0.0)
Requires-Dist: click (>=8.0.0,<9.0.0)
Requires-Dist: rich (>=12.6.0,<13.0.0)
Requires-Dist: typer (>=0.6.1,<0.7.0)
Project-URL: Bug Tracker, https://github.com/Aditya-Gupta1/track-job-applications/issues
Project-URL: Documentation, https://aditya-gupta1.github.io/track-job-applications/
Project-URL: Repository, https://github.com/Aditya-Gupta1/track-job-applications
